metrics_gen/__init__.py
metrics_gen/deployment_generator.py
metrics_gen/metrics_generator.py
metrics_gen/static_data_generator.py
metrics_gen/deployment/__init__.py
metrics_gen/deployment/providers.py
metrics_gen/metric/__init__.py
metrics_gen/metric/metric.py
metrics_gen/metric/metric_group.py
metrics_gen/metric/metrics/__init__.py
metrics_gen/metric/metrics/normal.py
metrics_gen/metric/metrics/poisson.py
tests/__init__.py
tests/test_deployment.py
tests/test_metrics.py
tests/test_static_data.py
metrics_gen-0.2.2.dist-info/LICENSE
metrics_gen-0.2.2.dist-info/METADATA
metrics_gen-0.2.2.dist-info/WHEEL
metrics_gen-0.2.2.dist-info/top_level.txt
metrics_gen-0.2.2.dist-info/RECORD
