Metadata-Version: 2.1
Name: metrics-gen
Version: 0.2.2
Summary: Fake deployment and data generator
Home-page: https://github.com/mlrun/metrics-gen
Author: Avi Asulin
Author-email: avia@iguazio.com
Classifier: Programming Language :: Python :: 3
Classifier: License :: OSI Approved :: MIT License
Classifier: Operating System :: OS Independent
License-File: LICENSE
